{
    "profile": {
        "name": "Tianchu LI",
        "title": "Software & Interactive Media Developer",
        "tagline": "Building digital & fun experiences with code",
        "bio": "A passionate developer with expertise in building interactive real-time experiences and web applications. Always eager to try new technologies and create fun projects.",
        "location": "Singapore",
        "available": true
    },
    "contact": {
        "email": "tianchu0522@gamil.com",
        "phone": "+65 8881 9196",
        "telegram": "@tianchu0522"
    },
    "social": [
        {
            "platform": "GitHub",
            "url": "https://github.com/LiTianchu"
        },
        {
            "platform": "LinkedIn",
            "url": "https://www.linkedin.com/in/tianchu-li-92aa251b9"
        },
        {
            "platform": "X",
            "url": "https://x.com/tianchuli1"
        }
    ],
    "stats": {
        "yearsExperience": 4,
        "projectsCompleted": 20,
        "coffeeConsumed": 1000,
        "linesOfCode": 100000
    }
}
